setup_scripts/install_bazel.sh
setup_scripts/install_docker.sh
setup_scripts/install_gcloud.sh
setup_scripts/install_python.sh
setup_scripts/install_xmanager.sh
setup_scripts/setup_all.sh
setup_scripts/setup_gcp.sh
xmanager/xm_flags.py
xmanager/bazel/client.py
xmanager/bazel/file_utils.py
xmanager/cli/cli.py
xmanager/cloud/__init__.py
xmanager/cloud/auth.py
xmanager/cloud/auth_test.py
xmanager/cloud/build_image.py
xmanager/cloud/build_image_test.py
xmanager/cloud/cloud_build.py
xmanager/cloud/cloud_build_test.py
xmanager/cloud/docker_lib.py
xmanager/cloud/kubernetes.py
xmanager/cloud/kubernetes_test.py
xmanager/cloud/utils.py
xmanager/cloud/utils_test.py
xmanager/cloud/vertex.py
xmanager/cloud/vertex_test.py
xmanager/cloud/data/wrapped_entrypoint.sh
xmanager/contrib/__init__.py
xmanager/contrib/addressing.py
xmanager/contrib/addressing_test.py
xmanager/contrib/copybara.py
xmanager/contrib/executor_selector.py
xmanager/contrib/flow.py
xmanager/contrib/framework_defaults.py
xmanager/contrib/framework_defaults_test.py
xmanager/contrib/gcs.py
xmanager/contrib/gcs_test.py
xmanager/contrib/parameter_controller.py
xmanager/contrib/process_entry.py
xmanager/contrib/tensorboard.py
xmanager/contrib/tensorboard_test.py
xmanager/contrib/tpu.py
xmanager/contrib/xm_tensorflow.py
xmanager/contrib/xm_tensorflow_test.py
xmanager/docker/docker_adapter.py
xmanager/generated/build_event_stream_pb2.py
xmanager/generated/command_line_pb2.py
xmanager/generated/data_pb2.py
xmanager/generated/failure_details_pb2.py
xmanager/generated/invocation_policy_pb2.py
xmanager/generated/option_filters_pb2.py
xmanager/module_lazy_loader/lazy_loader_module_attrs_test.py
xmanager/module_lazy_loader/module_lazy_loader.py
xmanager/vizier/vizier_cloud/__init__.py
xmanager/vizier/vizier_cloud/study_factory.py
xmanager/vizier/vizier_cloud/vizier_controller.py
xmanager/vizier/vizier_cloud/vizier_exploration.py
xmanager/vizier/vizier_cloud/vizier_worker.py
xmanager/xm/__init__.py
xmanager/xm/async_packager.py
xmanager-0.7.1.dist-info/licenses/LICENSE
xmanager-0.7.1.dist-info/METADATA
xmanager-0.7.1.dist-info/WHEEL
xmanager-0.7.1.dist-info/entry_points.txt
xmanager-0.7.1.dist-info/top_level.txt
xmanager-0.7.1.dist-info/RECORD
