Metadata-Version: 2.4
Name: xmanager
Version: 0.7.1
Summary: A framework for managing machine learning experiments
Author: DeepMind Technologies Limited
Project-URL: Homepage, https://github.com/deepmind/xmanager
Project-URL: Issue tracker, https://github.com/deepmind/xmanager/issues
Requires-Python: >=3.10
License-File: LICENSE
Requires-Dist: absl-py
Requires-Dist: alembic==1.4.3
Requires-Dist: async_generator
Requires-Dist: attrs
Requires-Dist: cloud-sql-python-connector
Requires-Dist: docker
Requires-Dist: etils[epath]
Requires-Dist: google-api-core
Requires-Dist: google-api-python-client
Requires-Dist: google-auth
Requires-Dist: google-cloud-aiplatform
Requires-Dist: google-cloud-storage
Requires-Dist: humanize
Requires-Dist: immutabledict
Requires-Dist: kubernetes
Requires-Dist: pyyaml
Requires-Dist: sqlalchemy==1.2.19
Requires-Dist: sqlparse
Requires-Dist: termcolor
Dynamic: author
Dynamic: description
Dynamic: description-content-type
Dynamic: license-file
Dynamic: project-url
Dynamic: requires-dist
Dynamic: requires-python
Dynamic: summary
